[
    {
        "turn": 1,
        "speaker": "A",
        "utterance": "The Blacks got divorced .",
        "emotion": "neutral",
        "text": "The Blacks got divorced .",
        "id": 1
    },
    {
        "turn": 2,
        "speaker": "B",
        "utterance": "Really ? Why ?",
        "emotion": "surprise",
        "expanded emotion cause evidence": [
            1
        ],
        "expanded emotion cause span": [
            "The Blacks got divorced ."
        ],
        "type": [
            "inter-personal"
        ],
        "text": "Really ? Why ?",
        "id": 2
    },
    {
        "turn": 3,
        "speaker": "A",
        "utterance": "Mr . Black has been getting a little on the side .",
        "emotion": "neutral",
        "text": "Mr . Black has been getting a little on the side .",
        "id": 3
    },
    {
        "turn": 4,
        "speaker": "B",
        "utterance": "Really ? I am surprised . He doesn't look like a guy who'd ever cheat on his wife , does he ?",
        "emotion": "neutral",
        "text": "Really ? I am surprised . He doesn't look like a guy who'd ever cheat on his wife , does he ?",
        "id": 4
    },
    {
        "turn": 5,
        "speaker": "A",
        "utterance": "No , he doesn't . Anyway , his wife found out that he has been two-timing for a long time .",
        "emotion": "neutral",
        "text": "No , he doesn't . Anyway , his wife found out that he has been two-timing for a long time .",
        "id": 5
    },
    {
        "turn": 6,
        "speaker": "B",
        "utterance": "Well , I am really surprised . By the way , have you done anything behind my back ?",
        "emotion": "surprise",
        "expanded emotion cause evidence": [
            4,
            5
        ],
        "expanded emotion cause span": [
            "He doesn't look like a guy who'd ever cheat on his wife",
            "his wife found out that he has been two-timing for a long time ."
        ],
        "type": [
            "hybrid"
        ],
        "text": "Well , I am really surprised . By the way , have you done anything behind my back ?",
        "id": 6
    },
    {
        "turn": 7,
        "speaker": "A",
        "utterance": "No . The only thing I've ever done behind your back is zipping you up .",
        "emotion": "happiness",
        "explanation": "the speaker is making a joke",
        "expanded emotion cause evidence": [
            7
        ],
        "expanded emotion cause span": [
            "The only thing I've ever done behind your back is zipping you up ."
        ],
        "type": [
            "no-context"
        ],
        "text": "No . The only thing I've ever done behind your back is zipping you up .",
        "id": 7
    },
    {
        "turn": 8,
        "speaker": "B",
        "utterance": "I like that joke , but I hope it's true .",
        "emotion": "happiness",
        "expanded emotion cause evidence": [
            7
        ],
        "expanded emotion cause span": [
            "The only thing I've ever done behind your back is zipping you up ."
        ],
        "type": [
            "inter-personal"
        ],
        "text": "I like that joke , but I hope it's true .",
        "id": 8,
        "source_sentences": [
            6
        ],
        "has_target": true,
        "annotator": "ground_truth"
    }
]