[
    {
        "turn": 12,
        "speaker": "B",
        "utterance": "Thanks .",
        "emotion": "happiness",
        "expanded emotion cause evidence": [
            11
        ],
        "expanded emotion cause span": [
            "If you want , I can give you some information I have about the city ."
        ],
        "type": [
            "inter-personal"
        ],
        "text": "Thanks .",
        "id": 12,
        "source_sentences": [
            10
        ],
        "has_target": true,
        "annotator": "ground_truth"
    }
]