[
    {
        "turn": 12,
        "speaker": "B",
        "utterance": "He certainly looks interested , doesn ' t he ? Shall we invite him over to our table ?",
        "emotion": "happiness",
        "expanded emotion cause evidence": [
            11,
            12
        ],
        "expanded emotion cause span": [
            "I think he fancies you .",
            "He certainly looks interested ,"
        ],
        "type": [
            "no-context",
            "inter-personal"
        ],
        "text": "He certainly looks interested , doesn ' t he ? Shall we invite him over to our table ?",
        "id": 12,
        "source_sentences": [
            10
        ],
        "has_target": true,
        "annotator": "ground_truth"
    }
]